langchain_tengits/__about__.py
langchain_tengits/__init__.py
langchain_tengits/chat_tengits.py
langchain_tengits/embedding_tengits.py
langchain_tengits/shcema.py
langchain_tengits/tengits_chat_model.py
langchain_tengits-0.0.3.dist-info/METADATA
langchain_tengits-0.0.3.dist-info/WHEEL
langchain_tengits-0.0.3.dist-info/licenses/LICENSE.txt
langchain_tengits-0.0.3.dist-info/RECORD
