Metadata-Version: 2.4
Name: langchain-tengits
Version: 0.0.3
Project-URL: Documentation, https://github.com/U.N. Owen/langchain-tengits#readme
Project-URL: Issues, https://github.com/U.N. Owen/langchain-tengits/issues
Project-URL: Source, https://github.com/U.N. Owen/langchain-tengits
Author-email: Muted Code <chenshiwu@tengits.com>
License-Expression: MIT
License-File: LICENSE.txt
Classifier: Development Status :: 4 - Beta
Classifier: Programming Language :: Python
Classifier: Programming Language :: Python :: 3.8
Classifier: Programming Language :: Python :: 3.9
Classifier: Programming Language :: Python :: 3.10
Classifier: Programming Language :: Python :: 3.11
Classifier: Programming Language :: Python :: 3.12
Classifier: Programming Language :: Python :: Implementation :: CPython
Classifier: Programming Language :: Python :: Implementation :: PyPy
Requires-Python: >=3.12
